LICENSE
gwlandscape_python/__init__.py
gwlandscape_python/dataset_type.py
gwlandscape_python/gwlandscape.py
gwlandscape_python/keyword_type.py
gwlandscape_python/model_type.py
gwlandscape_python/publication_type.py
gwlandscape_python/settings.py
gwlandscape_python/tests/__init__.py
gwlandscape_python/tests/conftest.py
gwlandscape_python/tests/test_dataset_type.py
gwlandscape_python/tests/test_gwlandscape_python.py
gwlandscape_python/tests/test_keyword_type.py
gwlandscape_python/tests/test_model_type.py
gwlandscape_python/tests/test_publication_type.py
gwlandscape_python/tests/utils.py
gwlandscape_python/utils/__init__.py
gwlandscape_python/utils/file_download.py
gwlandscape_python/utils/file_filters.py
gwlandscape_python/utils/identifiers.py
gwlandscape_python/utils/tests/test_file_filters.py
gwlandscape_python/utils/tests/test_identifiers.py
gwlandscape_python/utils/tests/test_utils.py
gwlandscape_python/utils/utils.py
gwlandscape_python-1.0.0.dist-info/LICENSE
gwlandscape_python-1.0.0.dist-info/METADATA
gwlandscape_python-1.0.0.dist-info/WHEEL
gwlandscape_python-1.0.0.dist-info/RECORD
